pkgdev/__init__.py
pkgdev/__main__.py
pkgdev/_verinfo.py
pkgdev/cli.py
pkgdev/const.py
pkgdev/git.py
pkgdev/mangle.py
pkgdev/_vendor/__init__.py
pkgdev/_vendor/tabulate.py
pkgdev/scripts/__init__.py
pkgdev/scripts/argparsers.py
pkgdev/scripts/pkgdev.py
pkgdev/scripts/pkgdev_bugs.py
pkgdev/scripts/pkgdev_commit.py
pkgdev/scripts/pkgdev_manifest.py
pkgdev/scripts/pkgdev_mask.py
pkgdev/scripts/pkgdev_push.py
pkgdev/scripts/pkgdev_showkw.py
pkgdev/scripts/pkgdev_tatt.py
pkgdev/tatt/__init__.py
pkgdev/tatt/template.sh.jinja
pkgdev-0.2.12.data/data/share/bash-completion/completions/pkgdev
pkgdev-0.2.12.data/data/share/zsh/site-functions/_pkgdev
pkgdev-0.2.12.dist-info/entry_points.txt
pkgdev-0.2.12.dist-info/licenses/LICENSE
pkgdev-0.2.12.dist-info/WHEEL
pkgdev-0.2.12.dist-info/METADATA
pkgdev-0.2.12.dist-info/RECORD
