Metadata-Version: 2.4
Name: pkgdev
Version: 0.2.12
Summary: collection of tools for Gentoo development
Author-email: Tim Harder <radhermit@gmail.com>, Arthur Zamarin <arthurzam@gentoo.org>
Maintainer-email: Arthur Zamarin <arthurzam@gentoo.org>
Requires-Python: ~=3.11
Classifier: License :: OSI Approved :: BSD License
Classifier: Programming Language :: Python :: 3.11
Classifier: Programming Language :: Python :: 3.12
Classifier: Programming Language :: Python :: 3.13
Classifier: Programming Language :: Python :: 3.14
License-File: LICENSE
Requires-Dist: snakeoil~=0.10.1
Requires-Dist: pkgcore~=0.12.30
Requires-Dist: pkgcheck~=0.10.36
Requires-Dist: sphinx ; extra == "doc"
Requires-Dist: nattka ; extra == "tatt"
Requires-Dist: Jinja2 ; extra == "tatt"
Requires-Dist: pytest>=6.0 ; extra == "test"
Requires-Dist: pytest-cov ; extra == "test"
Project-URL: Documentation, https://pkgcore.github.io/pkgdev/
Project-URL: Homepage, https://github.com/pkgcore/pkgdev
Project-URL: Source, https://github.com/pkgcore/pkgdev
Provides-Extra: doc
Provides-Extra: tatt
Provides-Extra: test
